{
	"version": 1.1,
	"tags": [
		{
			"name": "button",
			"description": "A button means an operation (or a series of operations). Clicking a button will trigger corresponding business logic.",
			"attributes": [
				{
					"name": "nz-button",
					"description": "nz-button directive is required for antd to work"
				},
				{
					"name": "nzType",
					"valueSet": "buttonTypes",
					"description": "In Ant Design, 4 types of button are provided. primary, default, dashed, text"
				}
			],
			"references": [
				{
					"name": "Angular Ant Design Buttons",
					"url": "https://ng.ant.design/components/button/en"
				}
			]
		},
		{
			"name": "nz-card",
			"description": "A card can be used to display content related to a single subject. The content can consist of multiple elements of varying types and sizes.",
			"attributes": [
				{
					"name": "nzActions",
					"description": "The action list, shows at the bottom of the Card."
				},
				{
					"name": "nzBorderless",
					"valueSet": "booleanValues",
					"description": "Remove border around the card"
				},
				{
					"name": "nzCover",
					"description": "Card cover"
				},
				{
					"name": "nzExtra",
					"description": "Content to render in the top-right corner of the card"
				},
				{
					"name": "nzHoverable",
					"valueSet": "booleanValues",
					"description": "Lift up when hovering card"
				},
				{
					"name": "nzLoading",
					"valueSet": "booleanValues",
					"description": "Shows a loading indicator while the contents of the card are being fetched"
				},
				{
					"name": "nzTitle",
					"valueSet": "booleanValues",
					"description": "Card title"
				},
				{
					"name": "nzType",
					"valueSet": "booleanValues",
					"description": "Card style type, can be set to `inner` or not set"
				},
				{
					"name": "nzSize",
					"valueSet": "componentSizes",
					"description": "Size of card"
				}
			],
			"references": [
				{
					"name": "Angular Ant Design Card",
					"url": "https://ng.ant.design/components/card/en"
				}
			]
		}
	],
	"globalAttributes": [
		{
			"name": "nz-typography",
			"description": {
				"kind": "markdown",
				"value": "Angular Antd [Typography](https://ng.ant.design/components/typography/en)"
			}
		},
		{
			"name": "nzOffset",
			"description": {
				"kind": "markdown",
				"value": "Angular Antd [Grid](https://ng.ant.design/components/grid/en#api)"
			}
		},
		{
			"name": "nzSpan",
			"description": {
				"kind": "markdown",
				"value": "Angular Antd [Grid](https://ng.ant.design/components/grid/en#api)"
			}
		},
		{
			"name": "nzXs",
			"description": {
				"kind": "markdown",
				"value": "Angular Antd [Grid](https://ng.ant.design/components/grid/en#api)"
			}
		},
		{
			"name": "nzSm",
			"description": {
				"kind": "markdown",
				"value": "Angular Antd [Grid](https://ng.ant.design/components/grid/en#api)"
			}
		},
		{
			"name": "nzMd",
			"description": {
				"kind": "markdown",
				"value": "Angular Antd [Grid](https://ng.ant.design/components/grid/en#api)"
			}
		},
		{
			"name": "nzLg",
			"description": {
				"kind": "markdown",
				"value": "Angular Antd [Grid](https://ng.ant.design/components/grid/en#api)"
			}
		},
		{
			"name": "nzXl",
			"description": {
				"kind": "markdown",
				"value": "Angular Antd [Grid](https://ng.ant.design/components/grid/en#api)"
			}
		},
		{
			"name": "nzXXl",
			"description": {
				"kind": "markdown",
				"value": "Angular Antd [Grid](https://ng.ant.design/components/grid/en#api)"
			}
		}
	],
	"valueSets": [
		{
			"name": "booleanValues",
			"values": [
				{
					"name": "true",
					"description": "True value of Boolean"
				},
				{
					"name": "false",
					"description": "false value of Boolean"
				}
			]
		},
		{
			"name": "buttonTypes",
			"values": [
				{
					"name": "primary",
					"description": "indicate the main action, one primary button at most in one section."
				},
				{
					"name": "default",
					"description": "indicate a series of actions without priority."
				},
				{
					"name": "dashed",
					"description": "used for adding action commonly."
				},
				{
					"name": "text",
					"description": "used for the most secondary action."
				},
				{
					"name": "link",
					"description": "used for external links."
				}
			]
		},
		{
			"name": "componentSizes",
			"values": [
				{
					"name": "default"
				},
				{
					"name": "small"
				},
				{
					"name": "large"
				}
			]
		}
	]
}
